README.md
setup.py
sqlfocus/__init__.py
sqlfocus/core.py
sqlfocus/field.py
sqlfocus/helpers.py
sqlfocus/table.py
sqlfocus.egg-info/PKG-INFO
sqlfocus.egg-info/SOURCES.txt
sqlfocus.egg-info/dependency_links.txt
sqlfocus.egg-info/top_level.txt