Metadata-Version: 2.1
Name: sqlfocus
Version: 0.3.0
Summary: UNKNOWN
Home-page: https://github.com/jDan735/sqlfocus
Author: Daniel Zakharov
Author-email: daniel734@bk.ru
License: MIT
Platform: UNKNOWN
Classifier: Programming Language :: Python :: 3
Classifier: Programming Language :: Python :: 3.5
Classifier: Programming Language :: Python :: 3.6
Classifier: Programming Language :: Python :: 3.7
Classifier: Programming Language :: Python :: 3.8
Classifier: License :: OSI Approved :: MIT License
Requires-Python: >=3
